[{"ID":"901234567-8","Name":"Banco XYZ","PhoneNumer":"323-456-7890","Email":"contact@bankxyz.com","Website":"www.bankofa.com","CompanySize":"Mediana","CompanyLogo":"BKA12345","PrimaryContact":"John Doe","SecondContact":"Maya Hawke"},{"ID":"800123456-7","Name":"Global Trust Bank","PhoneNumer":"213-313-6714","Email":"info@globaltrust.com","Website":"www.globaltrust.com","CompanySize":"Grande","CompanyLogo":"GTB67890","PrimaryContact":"Tom Odell","SecondContact":"Zoe Carter"},{"ID":"789012345-6","Name":"Union Finance","PhoneNumer":"605-945-1253","Email":"support@unionfinance.com","Website":"www.unionfinance.com","CompanySize":"Grande","CompanyLogo":"UF12345","PrimaryContact":"Jane Adams","SecondContact":"Jim Croce"}]